README.md
setup.py
linkedin_post_scraper_with_python/__init__.py
linkedin_post_scraper_with_python.egg-info/PKG-INFO
linkedin_post_scraper_with_python.egg-info/SOURCES.txt
linkedin_post_scraper_with_python.egg-info/dependency_links.txt
linkedin_post_scraper_with_python.egg-info/requires.txt
linkedin_post_scraper_with_python.egg-info/top_level.txt